LICENSE
README.md
setup.py
asyncsqlite3/__init__.py
asyncsqlite3/_version.py
asyncsqlite3/context.py
asyncsqlite3/core.py
asyncsqlite3/cursor.py
asyncsqlite3/exceptions.py
asyncsqlite3/factory.py
asyncsqlite3/pool.py
asyncsqlite3/transaction.py
asyncsqlite3.egg-info/PKG-INFO
asyncsqlite3.egg-info/SOURCES.txt
asyncsqlite3.egg-info/dependency_links.txt
asyncsqlite3.egg-info/requires.txt
asyncsqlite3.egg-info/top_level.txt