Metadata-Version: 2.1
Name: asyncsqlite3
Version: 0.1.8
Summary: Asynchronous driver for sqlite3.
Home-page: https://github.com/Vladyslav49/asyncsqlite3
Author: Vladyslav49
License: MIT
Requires-Python: >=3.7
Provides-Extra: uvloop
License-File: LICENSE
